kode_rpc/__init__.py
kode_rpc/client.py
kode_rpc/method.py
kode_rpc/rabbitmq.py
kode_rpc/server.py
kode_rpc/util/__init__.py
kode_rpc/util/rpc.py
kode_rpc-0.0.8.dist-info/LICENSE
kode_rpc-0.0.8.dist-info/METADATA
kode_rpc-0.0.8.dist-info/WHEEL
kode_rpc-0.0.8.dist-info/top_level.txt
kode_rpc-0.0.8.dist-info/RECORD
