Metadata-Version: 2.1
Name: kode-rpc
Version: 0.0.8
Summary: Library to work with RPC
Home-page: UNKNOWN
Author: KODE
Author-email: ashelepov@kode-t.ru
License: MIT
Platform: UNKNOWN
Classifier: Programming Language :: Python :: 3.8
Classifier: License :: OSI Approved :: MIT License
Classifier: Operating System :: OS Independent
Requires-Python: ==3.8.*
Requires-Dist: aio-pika (==6.4.1)
